{
  "name": "Base16 Atelier Forest Light",
  "programs": [
    {
      "name": "bspwm",
      "settings": [
        {
          "name": "wallpaper",
          "value": "~/Pictures/wallpapers/empry-road.jpg"
        },
        {
          "name": "normal_border_color",
          "value": "#e6e2e0"
        },
        {
          "name": "urgent_border_color",
          "value": "#f22c40"
        },
        {
          "name": "focused_border_color",
          "value": "#df5320"
        },
        {
          "name": "presel_feedback_color",
          "value": "#df5320"
        },
        {
          "name": "active_border_color",
          "value": "#766e6b"
        },
        {
          "name": "border_width",
          "value": "2"
        },
        {
          "name": "window_gap",
          "value": "25"
        }
      ]
    },
    {
      "name": "polybar",
      "settings": [
        {
          "name": "bar",
          "value": "alpha"
        },
        {
          "name": "alpha_background",
          "value": "#f1efee"
        },
        {
          "name": "alpha_foreground",
          "value": "#2c2421"
        },
        {
          "name": "alpha_label",
          "value": "#7b9726"
        },
        {
          "name": "alpha_text",
          "value": "#766e6b"
        },
        {
          "name": "alpha_urgent",
          "value": "#f22c40"
        }
      ]
    },
    {
      "name": "alacritty",
      "settings": [
        {
          "name": "theme",
          "value": "~/.config/scrypts/themes/alacritty/base16-atelier-forest-light.yml"
        },
        {
          "name": "bold_font",
          "value": "Dina"
        },
        {
          "name": "normal_font",
          "value": "Dina"
        },
        {
          "name": "italic_font",
          "value": "Dina"
        },
        {
          "name": "bold_italic_font",
          "value": "Dina"
        },
        {
          "name": "font_size",
          "value": "9"
        },
        {
          "name": "y_offset",
          "value": "0"
        }
      ]
    },
    {
      "name": "neovim",
      "settings": [
        {
          "name": "colorscheme",
          "value": "base16-atelier-forest-light"
        },
        {
          "name": "termguicolors",
          "value": "set termguicolors"
        },
        {
          "name": "cursorline",
          "value": "set cursorline"
        }
      ]
    },
    {
      "name": "dunst",
      "settings": [
        {
          "name": "font",
          "value": "Fira Code 10"
        },
        {
          "name": "normal_frame_color",
          "value": "#df5320"
        },
        {
          "name": "critical_frame_color",
          "value": "#f22c40"
        },
        {
          "name": "critical_background_color",
          "value": "#f22c40"
        },
        {
          "name": "normal_background_color",
          "value": "#f1efee"
        },
        {
          "name": "low_background_color",
          "value": "#f1efee"
        },
        {
          "name": "critical_foreground_color",
          "value": "#f1efee"
        },
        {
          "name": "normal_foreground_color",
          "value": "#766e6b"
        },
        {
          "name": "low_foreground_color",
          "value": "#766e6b"
        }
      ]
    },
    {
      "name": "rofi",
      "settings": [
        {
          "name": "layout",
          "value": "center"
        },
        {
          "name": "background",
          "value": "#f1efee"
        },
        {
          "name": "background_alt",
          "value": "#f1efee90"
        },
        {
          "name": "foreground",
          "value": "#766e6b"
        },
        {
          "name": "selected_background",
          "value": "#df5320"
        },
        {
          "name": "selected_border",
          "value": "#c38418"
        }
      ]
    }
  ]
}