{
  "name": "Pywal",
  "programs": [
    {
      "name": "bspwm",
      "settings": [
        {
          "name": "wallpaper",
          "value": "/home/breton/Pictures/wallpapers/cactusish-plants.jpg"
        },
        {
          "name": "normal_border_color",
          "value": "#101412"
        },
        {
          "name": "urgent_border_color",
          "value": "#40AE45"
        },
        {
          "name": "focused_border_color",
          "value": "#4EA357"
        },
        {
          "name": "presel_feedback_color",
          "value": "#4EA357"
        },
        {
          "name": "active_border_color",
          "value": "#729d76"
        },
        {
          "name": "border_width",
          "value": "3"
        }
      ]
    },
    {
      "name": "polybar",
      "settings": [
        {
          "name": "bar",
          "value": "alpha"
        },
        {
          "name": "alpha_background",
          "value": "#101412"
        },
        {
          "name": "alpha_foreground",
          "value": "#729d76"
        },
        {
          "name": "alpha_label",
          "value": "#348D4A"
        },
        {
          "name": "alpha_text",
          "value": "#2F8D3A"
        },
        {
          "name": "alpha_urgent",
          "value": "#40AE45"
        },
        {
          "name": "alpha_surround",
          "value": "#4EA357"
        }
      ]
    },
    {
      "name": "alacritty",
      "settings": [
        {
          "name": "theme",
          "value": "~/.config/scrypts/themes/alacritty/pywal.yml"
        },
        {
          "name": "bold_font",
          "value": "Dina"
        },
        {
          "name": "normal_font",
          "value": "Dina"
        },
        {
          "name": "italic_font",
          "value": "Dina"
        },
        {
          "name": "bold_italic_font",
          "value": "Dina"
        },
        {
          "name": "font_size",
          "value": "9"
        },
        {
          "name": "y_offset",
          "value": "1"
        }
      ]
    },
    {
      "name": "neovim",
      "settings": [
        {
          "name": "colorscheme",
          "value": "pywal"
        },
        {
          "name": "termguicolors",
          "value": "set notermguicolors"
        },
        {
          "name": "cursorline",
          "value": "set cursorline"
        }
      ]
    },
    {
      "name": "dunst",
      "settings": [
        {
          "name": "font",
          "value": "Iosevka 10"
        },
        {
          "name": "normal_frame_color",
          "value": "#4EA357"
        },
        {
          "name": "critical_frame_color",
          "value": "#4EA357"
        },
        {
          "name": "critical_background_color",
          "value": "#4EA357"
        },
        {
          "name": "normal_background_color",
          "value": "#101412"
        },
        {
          "name": "low_background_color",
          "value": "#101412"
        },
        {
          "name": "critical_foreground_color",
          "value": "#101412"
        },
        {
          "name": "normal_foreground_color",
          "value": "#729d76"
        },
        {
          "name": "low_foreground_color",
          "value": "#729d76"
        }
      ]
    },
    {
      "name": "rofi",
      "settings": [
        {
          "name": "layout",
          "value": "center"
        },
        {
          "name": "background",
          "value": "#101412"
        },
        {
          "name": "background_alt",
          "value": "#10141290"
        },
        {
          "name": "foreground",
          "value": "#729d76"
        },
        {
          "name": "selected_border",
          "value": "#4EA357"
        },
        {
          "name": "selected_background",
          "value": "#a4e1aa"
        }
      ]
    }
  ]
}